syncgit/__init__.py
syncgit/_config.py
syncgit/_gitcmd.py
syncgit/_repo.py
syncgit/_threadloop.py
syncgit/_threadsafe_dict.py
syncgit-0.4.4.dist-info/LICENSE
syncgit-0.4.4.dist-info/METADATA
syncgit-0.4.4.dist-info/WHEEL
syncgit-0.4.4.dist-info/top_level.txt
syncgit-0.4.4.dist-info/RECORD
