Metadata-Version: 2.1
Name: syncgit
Version: 0.4.4
Summary: Sync python dicts, strings ad modules to git repository.
Home-page: https://github.com/RainingComputers/syncgit
Author: RainingComputers
Author-email: vishnu.vish.shankar@gmail.com
License: UNKNOWN
Keywords: syncgit
Platform: UNKNOWN
Classifier: Programming Language :: Python :: 3
Classifier: License :: OSI Approved :: MIT License
Classifier: Operating System :: OS Independent
Classifier: Development Status :: 3 - Alpha
Classifier: Topic :: Software Development :: Version Control :: Git
Classifier: Topic :: Utilities
Requires-Python: >=3.8
License-File: LICENSE
Requires-Dist: PyYAML
